{
    "updated_iso":  "2026-01-04T02:07:02.4657634Z",
    "epoch_s":  1767492422,
    "items":  {
                  "erasme":  {
                                 "url":  "https://raw.githubusercontent.com/Flo-App-bxl/TDID-Live/main/mirror_erasme/live_erasme_8.png",
                                 "file":  "mirror_erasme/live_erasme_8.png",
                                 "ts":  1767492422
                             },
                  "info_COM":  {
                                   "url":  "https://raw.githubusercontent.com/Flo-App-bxl/TDID-Live/main/info/info_com_1.png",
                                   "file":  "info/info_com_1.png",
                                   "ts":  1767492422
                               }
              }
}