{
    "updated_iso":  "2025-12-29T09:42:02.4307887Z",
    "epoch_s":  1767001322,
    "items":  {
                  "erasme":  {
                                 "url":  "https://raw.githubusercontent.com/Flo-App-bxl/TDID-Live/main/mirror_erasme/live_erasme_2.png",
                                 "file":  "mirror_erasme/live_erasme_2.png",
                                 "ts":  1767001322
                             },
                  "info_COM":  {
                                   "url":  "https://raw.githubusercontent.com/Flo-App-bxl/TDID-Live/main/info/info_com_3.png",
                                   "file":  "info/info_com_3.png",
                                   "ts":  1767001322
                               }
              }
}