{
    "updated_iso":  "2025-12-25T14:34:14.1361033Z",
    "epoch_s":  1766673254,
    "items":  {
                  "calcul":  {
                                 "url":  "https://raw.githubusercontent.com/Flo-App-bxl/TDID-Live/main/mirror_calcul/calcul_8.png",
                                 "file":  "mirror_calcul/calcul_8.png",
                                 "ts":  1766673254
                             },
                  "info_COM":  {
                                   "url":  "https://raw.githubusercontent.com/Flo-App-bxl/TDID-Live/main/info/info_com_10.png",
                                   "file":  "info/info_com_10.png",
                                   "ts":  1766673254
                               }
              }
}